MANIFEST.in
settings.ini
setup.py
package_test_123/__init__.py
package_test_123/module.py
package_test_123.egg-info/PKG-INFO
package_test_123.egg-info/SOURCES.txt
package_test_123.egg-info/dependency_links.txt
package_test_123.egg-info/requires.txt
package_test_123.egg-info/top_level.txt