Metadata-Version: 2.1
Name: package-test-123
Version: 0.0.7
Summary: description text
License: UNKNOWN
Platform: UNKNOWN
